yamldiff/__init__.py
yamldiff/dictdiff.py
yamldiff/scripts/main.py
yamldiff-0.3.dist-info/entry_points.txt
yamldiff-0.3.dist-info/LICENSE
yamldiff-0.3.dist-info/WHEEL
yamldiff-0.3.dist-info/METADATA
yamldiff-0.3.dist-info/RECORD
