Metadata-Version: 2.1
Name: yamldiff
Version: 0.3
Summary: A package to semantically diff yaml files on the console.
Author-email: Zahari Kassabov <zaharid@protonmail.com>
Classifier: License :: OSI Approved :: MIT License
Requires-Dist: blessings
Requires-Dist: ruamel.yaml
Project-URL: Home, https://github.com/Zaharid/yamldiff
